probabilit/__init__.py
probabilit/correlation.py
probabilit/distributions.py
probabilit/garbage_collector.py
probabilit/inspection.py
probabilit/modeling.py
probabilit/utils.py
probabilit-0.4.0.dist-info/licenses/COPYING
probabilit-0.4.0.dist-info/METADATA
probabilit-0.4.0.dist-info/WHEEL
probabilit-0.4.0.dist-info/top_level.txt
probabilit-0.4.0.dist-info/RECORD
