Metadata-Version: 2.4
Name: probabilit
Version: 0.4.0
Summary: A Python package for Monte Carlo sampling.
Author: Tommy, Knut, Feda
License-Expression: GPL-3.0-only
Project-URL: homepage, https://github.com/equinor/probabilit
Requires-Python: >=3.10
License-File: COPYING
Requires-Dist: numpy>=2
Requires-Dist: scipy
Requires-Dist: networkx
Requires-Dist: seaborn
Requires-Dist: pandas
Requires-Dist: cvxpy
Provides-Extra: dev
Requires-Dist: ruff; extra == "dev"
Requires-Dist: pytest; extra == "dev"
Dynamic: license-file
